magicmethods.py
magicmethods-0.1.3.dist-info/LICENSE
magicmethods-0.1.3.dist-info/METADATA
magicmethods-0.1.3.dist-info/WHEEL
magicmethods-0.1.3.dist-info/top_level.txt
magicmethods-0.1.3.dist-info/RECORD
